config_parser/__init__.py
config_parser/loader.py
config_parser/parser.py
bored_config_parser-0.1.1.dist-info/LICENSE
bored_config_parser-0.1.1.dist-info/WHEEL
bored_config_parser-0.1.1.dist-info/METADATA
bored_config_parser-0.1.1.dist-info/RECORD
